infinity_ai/__init__.py
infinity_ai/client.py
infinity_ai-1.1.1.dist-info/licenses/LICENSE
infinity_ai-1.1.1.dist-info/METADATA
infinity_ai-1.1.1.dist-info/WHEEL
infinity_ai-1.1.1.dist-info/top_level.txt
infinity_ai-1.1.1.dist-info/RECORD
